underflow/__init__.py
underflow/api.py
underflow/cli.py
underflow/settings.py
underflow/stackoverflow.py
underflow/telegram.py
underflow-0.1.0.dist-info/entry_points.txt
underflow-0.1.0.dist-info/WHEEL
underflow-0.1.0.dist-info/METADATA
underflow-0.1.0.dist-info/RECORD
